dry_webview-0.3.2.dist-info/METADATA
dry_webview-0.3.2.dist-info/WHEEL
dry_webview-0.3.2.dist-info/licenses/LICENSE
dry/dry.pyi
dry/interface.py
dry/py.typed
dry/__init__.py
dry/dry.cp313-win_amd64.pyd
dry_webview-0.3.2.dist-info/RECORD
