Metadata-Version: 2.4
Name: dry-webview
Version: 0.3.2
Classifier: Intended Audience :: Developers
Classifier: Programming Language :: Python :: Implementation :: CPython
Classifier: Programming Language :: Rust
Classifier: Operating System :: Microsoft :: Windows
Classifier: License :: OSI Approved :: MIT License
Classifier: Development Status :: 3 - Alpha
License-File: LICENSE
Summary: Use your web dev skills to design UIs for your Python apps with this simple, Rust-powered webview library.
Keywords: webview,gui,rust,ui,web,python
Author: Otávio Barradas
License: MIT
Requires-Python: >=3.11
Project-URL: Homepage, https://github.com/barradasotavio/dry
Project-URL: Repository, https://github.com/barradasotavio/dry.git
